{"totalPosts": 7066, "totalPostsFromIndia": 4062, "totalPostsWithTotalComp": 3430, "lastUpdated": "2022/03/02 09:41:18", "top20Companies": [["Amazon", 323], ["Microsoft", 182], ["Oracle", 113], ["Flipkart", 84], ["Google", 81], ["Goldman Sachs", 75], ["Paytm", 72], ["Walmart", 71], ["Ola", 64], ["Oyo", 61], ["Paypal", 53], ["Swiggy", 51], ["Wipro", 48], ["Adobe", 41], ["Infosys", 41], ["Salesforce", 40], ["Uber", 38], ["Vmware", 37], ["Arcesium", 36], ["Tcs", 35]], "mostOffersInLastMonth": [["Microsoft", 27], ["Amazon", 26], ["Google", 17], ["Flipkart", 15], ["Paytm", 11], ["Walmart", 10], ["Tekion", 7], ["Ibm", 7], ["Cognizant", 6], ["Swiggy", 6]]}